mm_poetry/__init__.py
mm_poetry/cli.py
mm_poetry-0.1.1.dist-info/METADATA
mm_poetry-0.1.1.dist-info/WHEEL
mm_poetry-0.1.1.dist-info/RECORD
